src/edge_detect.v
`default_nettype none
`timescale 1ns/1ps
module edge_detect (
    input wire              clk,
    input wire              signal,
    output wire             leading_edge_detect
    );

    reg q0, q1, q2;

    always @(posedge clk) begin
        q0 <= signal;
        q1 <= q0;
        q2 <= q1;
    end



    assign leading_edge_detect = ((q1 ^ q2) & q1);


endmodule

edge_detect.vcd
$date
	Thu Apr 11 00:26:30 2024
$end
$version
	Icarus Verilog
$end
$timescale
	1ps
$end
$scope module edge_detect $end
$var wire 1 ! clk $end
$var wire 1 " leading_edge_detect $end
$var wire 1 # signal $end
$var reg 1 $ q0 $end
$var reg 1 % q1 $end
$var reg 1 & q2 $end
$upscope $end
$enddefinitions $end
$comment Show the parameter values. $end
$dumpall
$end
#0
$dumpvars
x&
x%
1$
1#
x"
1!
$end
#5000000
0!
#10000000
1%
1!
#15000000
0!
#20000000
0"
1&
1!
#25000000
0!
0#
#30000000
0$
1!
#35000000
0!
#40000000
0%
1!
#45000000
0!
#50000000
0&
1$
1!
1#
#55000000
0!
#60000000
1"
1%
1!
#65000000
0!
#70000000
0"
1&
1!
#75000000
0!
0#
#80000000
0$
1!
#85000000
0!
#90000000
0%
1!
#95000000
0!
#100000000
0&
1$
1!
1#
#105000000
0!
#110000000
1"
1%
1!
#115000000
0!
#120000000
0"
1&
1!
#125000000
0!
0#
#130000000
0$
1!
#135000000
0!
#140000000
0%
1!
#145000000
0!
#150000000
0&
1$
1!
1#
#155000000
0!
#160000000
1"
1%
1!
#165000000
0!
#170000000
0"
1&
1!
#175000000
0!
0#
#180000000
0$
1!
#185000000
0!
#190000000
0%
1!
#195000000
0!
#200000000
0&
1$
1!
1#
#205000000
0!
#210000000
1"
1%
1!
#215000000
0!
#220000000
0"
1&
1!
#225000000
0!
0#
#230000000
0$
1!
#235000000
0!
#240000000
0%
1!
#245000000
0!
#250000000
0&
1$
1!
1#
#255000000
0!
#260000000
1"
1%
1!
#265000000
0!
#270000000
0"
1&
1!
#275000000
0!
0#
#280000000
0$
1!
#285000000
0!
#290000000
0%
1!
#295000000
0!
#300000000
0&
1$
1!
1#
#305000000
0!
#310000000
1"
1%
1!
#315000000
0!
#320000000
0"
1&
1!
#325000000
0!
0#
#330000000
0$
1!
#335000000
0!
#340000000
0%
1!
#345000000
0!
#350000000
0&
1$
1!
1#
#355000000
0!
#360000000
1"
1%
1!
#365000000
0!
#370000000
0"
1&
1!
#375000000
0!
0#
#380000000
0$
1!
#385000000
0!
#390000000
0%
1!
#395000000
0!
#400000000
0&
1$
1!
1#
#405000000
0!
#410000000
1"
1%
1!
#415000000
0!
#420000000
0"
1&
1!
#425000000
0!
0#
#430000000
0$
1!
#435000000
0!
#440000000
0%
1!
#445000000
0!
#450000000
0&
1$
1!
1#
#455000000
0!
#460000000
1"
1%
1!
#465000000
0!
#470000000
0"
1&
1!
#475000000
0!
0#
#480000000
0$
1!
#485000000
0!
#490000000
0%
1!
#495000000
0!
#500000000
0&
1$
1!
1#
#505000000
0!
#510000000
1"
1%
1!
#515000000
0!
#520000000
0"
1&
1!
#525000000
0!
0#
#530000000
0$
1!
#535000000
0!
#540000000
0%
1!
#545000000
0!
#550000000
0&
1$
1!
1#
#555000000
0!
#560000000
1"
1%
1!
#565000000
0!
#570000000
0"
1&
1!
#575000000
0!
0#
#580000000
0$
1!
#585000000
1#
0!
#590000000
0%
1$
1!
#595000000
0!
#600000000
1"
0&
1%
1!
#605000000
0!
#610000000
0"
1&
1!
#615000000
0!
#620000000
1!
#625000000
0!
#630000000
1!
#635000000
0!
0#
#640000000
0$
1!
#645000000
0!
#650000000
0%
1!
#655000000
0!
#660000000
0&
1!
#665000000
0!
#670000000
1!
#675000000
0!
#680000000
1!
#685000000
0!
1#
#690000000
1$
1!
#695000000
0!
#700000000
1"
1%
1!
#705000000
0!
#710000000
0"
1&
1!
#715000000
0!
#720000000
1!
#725000000
0!
#730000000
1!
#735000000
0!
0#
#740000000
0$
1!
#745000000
0!
#750000000
0%
1!
#755000000
0!
#760000000
0&
1!
#765000000
0!
#770000000
1!
#775000000
0!
#780000000
1!
#785000000
0!
1#
#790000000
1$
1!
#795000000
0!
#800000000
1"
1%
1!
#805000000
0!
#810000000
0"
1&
1!
#815000000
0!
#820000000
1!
#825000000
0!
#830000000
1!
#835000000
0!
0#
#840000000
0$
1!
#845000000
0!
#850000000
0%
1!
#855000000
0!
#860000000
0&
1!
#865000000
0!
#870000000
1!
#875000000
0!
#880000000
1!
#885000000
0!
1#
#890000000
1$
1!
#895000000
0!
#900000000
1"
1%
1!
#905000000
0!
#910000000
0"
1&
1!
#915000000
0!
#920000000
1!
#925000000
0!
#930000000
1!
#935000000
0!
0#
#940000000
0$
1!
#945000000
0!
#950000000
0%
1!
#955000000
0!
#960000000
0&
1!
#965000000
0!
#970000000
1!
#975000000
0!
#980000000
1!
#985000000
0!
1#
#990000000
1$
1!
#995000000
0!
#1000000000
1"
1%
1!
#1005000000
0!
#1010000000
0"
1&
1!
#1015000000
0!
#1020000000
1!
#1025000000
0!
#1030000000
1!
#1035000000
0!
0#
#1040000000
0$
1!
#1045000000
0!
#1050000000
0%
1!
#1055000000
0!
#1060000000
0&
1!
#1065000000
0!
#1070000000
1!
#1075000000
0!
#1080000000
1!
#1085000000
0!
1#
#1090000000
1$
1!
#1095000000
0!
#1100000000
1"
1%
1!
#1105000000
0!
#1110000000
0"
1&
1!
#1115000000
0!
#1120000000
1!
#1125000000
0!
#1130000000
1!
#1135000000
0!
0#
#1140000000
0$
1!
#1145000000
0!
#1150000000
0%
1!
#1155000000
0!
#1160000000
0&
1!
#1165000000
0!
#1170000000
1!
#1175000000
0!
#1180000000
1!
#1185000000
0!
1#
#1190000000
1$
1!
#1195000000
0!
#1200000000
1"
1%
1!
#1205000000
0!
#1210000000
0"
1&
1!
#1215000000
0!
#1220000000
1!
#1225000000
0!
#1230000000
1!
#1235000000
0!
0#
#1240000000
0$
1!
#1245000000
0!
#1250000000
0%
1!
#1255000000
0!
#1260000000
0&
1!
#1265000000
0!
#1270000000
1!
#1275000000
0!
#1280000000
1!
#1285000000
0!
1#
#1290000000
1$
1!
#1295000000
0!
#1300000000
1"
1%
1!
#1305000000
0!
#1310000000
0"
1&
1!
#1315000000
0!
#1320000000
1!
#1325000000
0!
#1330000000
1!
#1335000000
0!
0#
#1340000000
0$
1!
#1345000000
0!
#1350000000
0%
1!
#1355000000
0!
#1360000000
0&
1!
#1365000000
0!
#1370000000
1!
#1375000000
0!
#1380000000
1!
#1385000000
0!
1#
#1390000000
1$
1!
#1395000000
0!
#1400000000
1"
1%
1!
#1405000000
0!
#1410000000
0"
1&
1!
#1415000000
0!
#1420000000
1!
#1425000000
0!
#1430000000
1!
#1435000000
0!
0#
#1440000000
0$
1!
#1445000000
0!
#1450000000
0%
1!
#1455000000
0!
#1460000000
0&
1!
#1465000000
0!
#1470000000
1!
#1475000000
0!
#1480000000
1!
#1485000000
0!
1#
#1490000000
1$
1!
#1495000000
0!
#1500000000
1"
1%
1!
#1505000000
0!
#1510000000
0"
1&
1!
#1515000000
0!
#1520000000
1!
#1525000000
0!
#1530000000
1!
#1535000000
0!
0#
#1540000000
0$
1!
#1545000000
0!
#1550000000
0%
1!
#1555000000
0!
#1560000000
0&
1!
#1565000000
0!
#1570000000
1!
#1575000000
0!
#1580000000
1!
#1585000000
0!
1#
#1590000000
1$
1!
#1595000000
0!
#1600000000
1"
1%
1!
#1605000000
0!
#1610000000
0"
1&
1!
#1615000000
0!
#1620000000
1!
#1625000000
0!
#1630000000
1!
#1635000000
0!
#1640000000
1!
#1645000000
0!
#1650000000
1!
#1655000000
0!
#1660000000
1!
#1665000000
0!
#1670000000
1!
#1675000000
0!
#1680000000
1!
#1685000000
0!
#1690000000
1!
#1695000000
0!
#1700000000
1!
#1705000000
0!
#1710000000
1!
#1715000000
0!
#1720000000
1!
#1725000000
0!
#1730000000
1!
#1735000000
0!
#1740000000
1!
#1745000000
0!
#1750000000
1!
#1755000000
0!
#1760000000
1!
#1765000000
0!
#1770000000
1!
#1775000000
0!
#1780000000
1!
#1785000000
0!
#1790000000
1!
#1791500000
0#
#1795000000
0!
#1800000000
0$
1!
#1805000000
0!
#1810000000
0%
1!
#1815000000
0!
#1820000000
0&
1!
#1825000000
0!
#1830000000
1!
#1835000000
0!
#1840000000
1!
#1845000000
0!
#1850000000
1!
#1855000000
0!
#1860000000
1!
#1865000000
0!
#1870000000
1!
#1875000000
0!
#1880000000
1!
#1885000000
0!
#1890000000
1!
#1895000000
0!
#1900000000
1!
#1905000000
0!
#1910000000
1!
#1915000000
0!
#1920000000
1!
#1925000000
0!
#1930000000
1!
#1935000000
0!
#1940000000
1!
#1945000000
0!
#1950000000
1!
#1955000000
0!
#1958000000
1#
#1960000000
1$
1!
#1965000000
0!
#1970000000
1"
1%
1!
#1975000000
0!
#1980000000
0"
1&
1!
#1985000000
0!
#1990000000
1!
#1995000000
0!
#2000000000
1!
#2005000000
0!
#2010000000
1!
#2015000000
0!
#2020000000
1!
#2025000000
0!
#2030000000
1!
#2035000000
0!
#2040000000
1!
#2045000000
0!
#2050000000
1!
#2055000000
0!
#2060000000
1!
#2065000000
0!
#2070000000
1!
#2075000000
0!
#2080000000
1!
#2085000000
0!
#2090000000
1!
#2095000000
0!
#2100000000
1!
#2105000000
0!
#2110000000
1!
#2115000000
0!
#2120000000
1!
#2124500000
0#
#2125000000
0!
#2130000000
0$
1!
#2135000000
0!
#2140000000
0%
1!
#2145000000
0!
#2150000000
0&
1!
#2155000000
0!
#2160000000
1!
#2165000000
0!
#2170000000
1!
#2175000000
0!
#2180000000
1!
#2185000000
0!
#2190000000
1!
#2195000000
0!
#2200000000
1!
#2205000000
0!
#2210000000
1!
#2215000000
0!
#2220000000
1!
#2225000000
0!
#2230000000
1!
#2235000000
0!
#2240000000
1!
#2245000000
0!
#2250000000
1!
#2255000000
0!
#2260000000
1!
#2265000000
0!
#2270000000
1!
#2275000000
0!
#2280000000
1!
#2285000000
0!
#2290000000
1!
#2291000000
1#
#2295000000
0!
#2300000000
1$
1!
#2305000000
0!
#2310000000
1"
1%
1!
#2315000000
0!
#2320000000
0"
1&
1!
#2325000000
0!
#2330000000
1!
#2335000000
0!
#2340000000
1!
#2345000000
0!
#2350000000
1!
#2355000000
0!
#2360000000
1!
#2365000000
0!
#2370000000
1!
#2375000000
0!
#2380000000
1!
#2385000000
0!
#2390000000
1!
#2395000000
0!
#2400000000
1!
#2405000000
0!
#2410000000
1!
#2415000000
0!
#2420000000
1!
#2425000000
0!
#2430000000
1!
#2435000000
0!
#2440000000
1!
#2445000000
0!
#2450000000
1!
#2455000000
0!
#2457500000
0#
#2460000000
0$
1!
#2465000000
0!
#2470000000
0%
1!
#2475000000
0!
#2480000000
0&
1!
#2485000000
0!
#2490000000
1!
#2495000000
0!
#2500000000
1!
#2505000000
0!
#2510000000
1!
#2515000000
0!
#2520000000
1!
#2525000000
0!
#2530000000
1!
#2535000000
0!
#2540000000
1!
#2545000000
0!
#2550000000
1!
#2555000000
0!
#2560000000
1!
#2565000000
0!
#2570000000
1!
#2575000000
0!
#2580000000
1!
#2585000000
0!
#2590000000
1!
#2595000000
0!
#2600000000
1!
#2605000000
0!
#2610000000
1!
#2615000000
0!
#2620000000
1!
#2624000000
1#
#2625000000
0!
#2630000000
1$
1!
#2635000000
0!
#2640000000
1"
1%
1!
#2645000000
0!
#2650000000
0"
1&
1!
#2655000000
0!
#2660000000
1!
#2665000000
0!
#2670000000
1!
#2675000000
0!
#2680000000
1!
#2685000000
0!
#2690000000
1!
#2695000000
0!
#2700000000
1!
#2705000000
0!
#2710000000
1!
#2715000000
0!
#2720000000
1!
#2725000000
0!
#2730000000
1!
#2735000000
0!
#2740000000
1!
#2745000000
0!
#2750000000
1!
#2755000000
0!
#2760000000
1!
#2765000000
0!
#2770000000
1!
#2775000000
0!
#2780000000
1!
#2785000000
0!
#2790000000
1!
#2790500000
0#
#2795000000
0!
#2800000000
0$
1!
#2805000000
0!
#2810000000
0%
1!
#2815000000
0!
#2820000000
0&
1!
#2825000000
0!
#2830000000
1!
#2835000000
0!
#2840000000
1!
#2845000000
0!
#2850000000
1!
#2855000000
0!
#2860000000
1!
#2865000000
0!
#2870000000
1!
#2875000000
0!
#2880000000
1!
#2885000000
0!
#2890000000
1!
#2895000000
0!
#2900000000
1!
#2905000000
0!
#2910000000
1!
#2915000000
0!
#2920000000
1!
#2925000000
0!
#2930000000
1!
#2935000000
0!
#2940000000
1!
#2945000000
0!
#2950000000
1!
#2955000000
0!
#2957000000
1#
#2960000000
1$
1!
#2965000000
0!
#2970000000
1"
1%
1!
#2975000000
0!
#2980000000
0"
1&
1!
#2985000000
0!
#2990000000
1!
#2995000000
0!
#3000000000
1!
#3005000000
0!
#3010000000
1!
#3015000000
0!
#3020000000
1!
#3025000000
0!
#3030000000
1!
#3035000000
0!
#3040000000
1!
#3045000000
0!
#3050000000
1!
#3055000000
0!
#3060000000
1!
#3065000000
0!
#3070000000
1!
#3075000000
0!
#3080000000
1!
#3085000000
0!
#3090000000
1!
#3095000000
0!
#3100000000
1!
#3105000000
0!
#3110000000
1!
#3115000000
0!
#3120000000
1!
#3123500000
0#
#3125000000
0!
#3130000000
0$
1!
#3135000000
0!
#3140000000
0%
1!
#3145000000
0!
#3150000000
0&
1!
#3155000000
0!
#3160000000
1!
#3165000000
0!
#3170000000
1!
#3175000000
0!
#3180000000
1!
#3185000000
0!
#3190000000
1!
#3195000000
0!
#3200000000
1!
#3205000000
0!
#3210000000
1!
#3215000000
0!
#3220000000
1!
#3225000000
0!
#3230000000
1!
#3235000000
0!
#3240000000
1!
#3245000000
0!
#3250000000
1!
#3255000000
0!
#3260000000
1!
#3265000000
0!
#3270000000
1!
#3275000000
0!
#3280000000
1!
#3285000000
0!
#3290000000
1$
1!
1#
#3295000000
0!
#3300000000
1"
1%
1!
#3305000000
0!
#3310000000
0"
1&
1!
#3315000000
0!
#3320000000
1!
#3325000000
0!
#3330000000
1!
#3335000000
0!
#3340000000
1!
#3345000000
0!
#3350000000
1!
#3355000000
0!
#3360000000
1!
#3365000000
0!
#3370000000
1!
#3375000000
0!
#3380000000
1!
#3385000000
0!
#3390000000
1!
#3395000000
0!
#3400000000
1!
#3405000000
0!
#3410000000
1!
#3415000000
0!
#3420000000
1!
#3425000000
0!
#3430000000
1!
#3435000000
0!
#3440000000
1!
#3445000000
0!
#3450000000
1!
#3455000000
0!
#3456500000
0#
#3460000000
0$
1!
#3465000000
0!
#3470000000
0%
1!
#3475000000
0!
#3480000000
0&
1!
#3485000000
0!
#3490000000
1!
#3495000000
0!
#3500000000
1!
#3505000000
0!
#3510000000
1!
#3515000000
0!
#3520000000
1!
#3525000000
0!
#3530000000
1!
#3535000000
0!
#3540000000
1!
#3545000000
0!
#3550000000
1!
#3555000000
0!
#3560000000
1!
#3565000000
0!
#3570000000
1!
#3575000000
0!
#3580000000
1!
#3585000000
0!
#3590000000
1!
#3595000000
0!
#3600000000
1!
#3605000000
0!
#3610000000
1!
#3615000000
0!
#3620000000
1!
#3623000000
1#
#3625000000
0!
#3630000000
1$
1!
#3635000000
0!
#3640000000
1"
1%
1!
#3645000000
0!
#3650000000
0"
1&
1!
#3655000000
0!
#3660000000
1!
#3665000000
0!
#3670000000
1!
#3675000000
0!
#3680000000
1!
#3685000000
0!
#3690000000
1!
#3695000000
0!
#3700000000
1!
#3705000000
0!
#3710000000
1!
#3715000000
0!
#3720000000
1!
#3725000000
0!
#3730000000
1!
#3735000000
0!
#3740000000
1!
#3745000000
0!
#3750000000
1!
#3755000000
0!
#3760000000
1!
#3765000000
0!
#3770000000
1!
#3775000000
0!
#3780000000
1!
#3785000000
0!
#3789500000
0#
#3790000000
0$
1!
#3795000000
0!
#3800000000
0%
1!
#3805000000
0!
#3810000000
0&
1!
#3815000000
0!
#3820000000
1!
#3825000000
0!
#3830000000
1!
#3835000000
0!
#3840000000
1!
#3845000000
0!
#3850000000
1!
#3855000000
0!
#3860000000
1!
#3865000000
0!
#3870000000
1!
#3875000000
0!
#3880000000
1!
#3885000000
0!
#3890000000
1!
#3895000000
0!
#3900000000
1!
#3905000000
0!
#3910000000
1!
#3915000000
0!
#3920000000
1!
#3925000000
0!
#3930000000
1!
#3935000000
0!
#3940000000
1!
#3945000000
0!
#3950000000
1!
#3955000000
0!
#3956000000
1#
#3960000000
1$
1!
#3965000000
0!
#3970000000
1"
1%
1!
#3975000000
0!
#3980000000
0"
1&
1!
#3985000000
0!
#3990000000
1!
#3995000000
0!
#4000000000
1!
#4005000000
0!
#4010000000
1!
#4015000000
0!
#4020000000
1!
#4025000000
0!
#4030000000
1!
#4035000000
0!
#4040000000
1!
#4045000000
0!
#4050000000
1!
#4055000000
0!
#4060000000
1!
#4065000000
0!
#4070000000
1!
#4075000000
0!
#4080000000
1!
#4085000000
0!
#4090000000
1!
#4095000000
0!
#4100000000
1!
#4105000000
0!
#4110000000
1!
#4115000000
0!
#4120000000
1!
#4122500000
0#
#4125000000
0!
#4130000000
0$
1!
#4135000000
0!
#4140000000
0%
1!
#4145000000
0!
#4150000000
0&
1!
#4155000000
0!
#4160000000
1!
#4165000000
0!
#4170000000
1!
#4175000000
0!
#4180000000
1!
#4185000000
0!
#4190000000
1!
#4195000000
0!
#4200000000
1!
#4205000000
0!
#4210000000
1!
#4215000000
0!
#4220000000
1!
#4225000000
0!
#4230000000
1!
#4235000000
0!
#4240000000
1!
#4245000000
0!
#4250000000
1!
#4255000000
0!
#4260000000
1!
#4265000000
0!
#4270000000
1!
#4275000000
0!
#4280000000
1!
#4285000000
0!
#4289000000
1#
#4290000000
1$
1!
#4295000000
0!
#4300000000
1"
1%
1!
#4305000000
0!
#4310000000
0"
1&
1!
#4315000000
0!
#4320000000
1!
#4325000000
0!
#4330000000
1!
#4335000000
0!
#4340000000
1!
#4345000000
0!
#4350000000
1!
#4355000000
0!
#4360000000
1!
#4365000000
0!
#4370000000
1!
#4375000000
0!
#4380000000
1!
#4385000000
0!
#4390000000
1!
#4395000000
0!
#4400000000
1!
#4405000000
0!
#4410000000
1!
#4415000000
0!
#4420000000
1!
#4425000000
0!
#4430000000
1!
#4435000000
0!
#4440000000
1!
#4445000000
0!
#4450000000
1!
#4455000000
0!
#4455500000
0#
#4460000000
0$
1!
#4465000000
0!
#4470000000
0%
1!
#4475000000
0!
#4480000000
0&
1!
#4485000000
0!
#4490000000
1!
#4495000000
0!
#4500000000
1!
#4505000000
0!
#4510000000
1!
#4515000000
0!
#4520000000
1!
#4525000000
0!
#4530000000
1!
#4535000000
0!
#4540000000
1!
#4545000000
0!
#4550000000
1!
#4555000000
0!
#4560000000
1!
#4565000000
0!
#4570000000
1!
#4575000000
0!
#4580000000
1!
#4585000000
0!
#4590000000
1!
#4595000000
0!
#4600000000
1!
#4605000000
0!
#4610000000
1!
#4615000000
0!
#4620000000
1!
#4622000000
1#
#4625000000
0!
#4630000000
1$
1!
#4635000000
0!
#4640000000
1"
1%
1!
#4645000000
0!
#4650000000
0"
1&
1!
#4655000000
0!
#4660000000
1!
#4665000000
0!
#4670000000
1!
#4675000000
0!
#4680000000
1!
#4685000000
0!
#4690000000
1!
#4695000000
0!
#4700000000
1!
#4705000000
0!
#4710000000
1!
#4715000000
0!
#4720000000
1!
#4725000000
0!
#4730000000
1!
#4735000000
0!
#4740000000
1!
#4745000000
0!
#4750000000
1!
#4755000000
0!
#4760000000
1!
#4765000000
0!
#4770000000
1!
#4775000000
0!
#4780000000
1!
#4785000000
0!
#4788500000
0#
#4790000000
0$
1!
#4795000000
0!
#4800000000
0%
1!
#4805000000
0!
#4810000000
0&
1!
#4815000000
0!
#4820000000
1!
#4825000000
0!
#4830000000
1!
#4835000000
0!
#4840000000
1!
#4845000000
0!
#4850000000
1!
#4855000000
0!
#4860000000
1!
#4865000000
0!
#4870000000
1!
#4875000000
0!
#4880000000
1!
#4885000000
0!
#4890000000
1!
#4895000000
0!
#4900000000
1!
#4905000000
0!
#4910000000
1!
#4915000000
0!
#4920000000
1!
#4925000000
0!
#4930000000
1!
#4935000000
0!
#4940000000
1!
#4945000000
0!
#4950000000
1!
#4955000000
0!
1#
#4960000000
1$
1!
#4965000000
0!
#4970000000
1"
1%
1!
#4975000000
0!
#4980000000
0"
1&
1!
