src/seven_segment.v
`default_nettype none
`timescale 1ns/1ps
module seven_segment (
    input wire          clk,
    input wire          reset,
    input wire          load,
    input wire [3:0]    ten_count,
    input wire [3:0]    unit_count,
    output reg [6:0]    segments,
    output reg          digit
);

    reg [3:0] ten_count_reg;
    reg [3:0] unit_count_reg;
    wire [3:0] decode;

    always @(posedge clk) begin

        if(reset) begin

            digit <= 0;
            ten_count_reg <= 0;
            unit_count_reg <= 0;

        end else begin

            if(load) begin
                ten_count_reg   <= ten_count;
                unit_count_reg  <= unit_count;
            end

            digit <= ! digit;
        end
    end

    assign decode = digit ? ten_count_reg : unit_count_reg;

    always @(*) begin
        case(decode)
            //                7654321
            0:  segments = 7'b0111111;
            1:  segments = 7'b0000110;
            2:  segments = 7'b1011011;
            3:  segments = 7'b1001111;
            4:  segments = 7'b1100110;
            5:  segments = 7'b1101101;
            6:  segments = 7'b1111100;
            7:  segments = 7'b0000111;
            8:  segments = 7'b1111111;
            9:  segments = 7'b1100111;
            default:
                segments = 7'b0000000;
        endcase
    end

endmodule

src/edge_detect.v
`default_nettype none
`timescale 1ns/1ps
module edge_detect (
    input wire              clk,
    input wire              signal,
    output wire             leading_edge_detect
    );

    reg q0, q1, q2;

    always @(posedge clk) begin
        q0 <= signal;
        q1 <= q0;
        q2 <= q1;
    end



    assign leading_edge_detect = ((q1 ^ q2) & q1);


endmodule

src/frequency_counter.v
`default_nettype none
`timescale 1ns/1ps

module frequency_counter #(
    localparam UPDATE_PERIOD = 1200,
    localparam BITS = 12
)(
    input wire clk,
    input wire reset,
    input wire signal,
    input wire [BITS-1:0] period,
    input wire period_load,
    output wire [6:0] segments,
    output wire digit
);

// states
localparam STATE_COUNT = 0;
localparam STATE_TENS = 1;
localparam STATE_UNITS = 2;

reg [1:0] state;
reg [6:0] edge_counter; // need to count up to 99
reg [BITS-1:0] clock_counter;


reg [BITS-1:0] update_period;



reg [3:0] ten_count;
reg [3:0] unit_count;
wire leading_edge_detect;

edge_detect edge_detect0(.clk(clk), .signal(signal), .leading_edge_detect(leading_edge_detect));

reg load_digit;
seven_segment seven_segment0(.clk(clk), .reset(reset), .load(load_digit), .ten_count(ten_count), .unit_count(unit_count), .segments(segments), .digit(digit));



always @(posedge clk) begin
    if (reset)
        update_period <= UPDATE_PERIOD;
    else if(period_load) 
        update_period <= period;
end



always @(posedge clk) begin
    if (reset) begin
        state <= STATE_COUNT;
        edge_counter <= 0;
        clock_counter <= 0;
        ten_count <= 0;
        unit_count <= 0;
        load_digit <= 0;
    end else begin
        case (state)
            STATE_COUNT: begin

                load_digit <= 1'b0;
                ten_count <= 0;
                unit_count <= 0;


                // count edges and clock cycles
                if (leading_edge_detect)
                    edge_counter <= edge_counter + 1'b1;
                clock_counter <= clock_counter + 1'b1;

                // if clock cycles >= UPDATE_PERIOD then go to next state
                if (clock_counter == update_period -1) begin
                    state <= STATE_TENS;
                end
            end

            STATE_TENS: begin
                // count number of tens by subtracting 10 while edge counter >= 10
                if (edge_counter >= 10) begin
                    edge_counter <= edge_counter - 7'd10;
                    ten_count <= ten_count + 1'b1;
                end else begin
                    state <= STATE_UNITS;
                end
            end

            STATE_UNITS: begin
                // what is left in edge counter is units
                unit_count <= edge_counter;
                edge_counter <= 0;  // Reset edge_counter for the next counting period
                clock_counter <= 0;
                // update the display
                load_digit <= 1;

                // go back to counting
                state <= STATE_COUNT;
            end

            default: state <= STATE_COUNT;
        endcase
    end
end

endmodule

frequency_counter.vcd
$date
	Fri Apr 12 00:00:06 2024
$end
$version
	Icarus Verilog
$end
$timescale
	1ps
$end
$scope module frequency_counter $end
$var wire 1 ! clk $end
$var wire 12 " period [11:0] $end
$var wire 1 # period_load $end
$var wire 1 $ reset $end
$var wire 1 % signal $end
$var wire 7 & segments [6:0] $end
$var wire 1 ' leading_edge_detect $end
$var wire 1 ( digit $end
$var parameter 32 ) BITS $end
$var parameter 32 * STATE_COUNT $end
$var parameter 32 + STATE_TENS $end
$var parameter 32 , STATE_UNITS $end
$var parameter 32 - UPDATE_PERIOD $end
$var reg 12 . clock_counter [11:0] $end
$var reg 7 / edge_counter [6:0] $end
$var reg 1 0 load_digit $end
$var reg 2 1 state [1:0] $end
$var reg 4 2 ten_count [3:0] $end
$var reg 4 3 unit_count [3:0] $end
$var reg 12 4 update_period [11:0] $end
$scope module edge_detect0 $end
$var wire 1 ! clk $end
$var wire 1 ' leading_edge_detect $end
$var wire 1 % signal $end
$var reg 1 5 q0 $end
$var reg 1 6 q1 $end
$var reg 1 7 q2 $end
$upscope $end
$scope module seven_segment0 $end
$var wire 1 ! clk $end
$var wire 1 0 load $end
$var wire 1 $ reset $end
$var wire 4 8 ten_count [3:0] $end
$var wire 4 9 unit_count [3:0] $end
$var wire 4 : decode [3:0] $end
$var reg 1 ( digit $end
$var reg 7 ; segments [6:0] $end
$var reg 4 < ten_count_reg [3:0] $end
$var reg 4 = unit_count_reg [3:0] $end
$upscope $end
$upscope $end
$enddefinitions $end
$comment Show the parameter values. $end
$dumpall
b10010110000 -
b10 ,
b1 +
b0 *
b1100 )
$end
#0
$dumpvars
b0 =
b0 <
b111111 ;
b0 :
b0 9
b0 8
x7
x6
z5
b10010110000 4
b0 3
b0 2
b0 1
00
b0 /
b0 .
0(
x'
b111111 &
z%
1$
0#
bz "
1!
$end
#5000000
0!
#10000000
z6
1!
#15000000
0!
#20000000
z7
1!
#25000000
0!
#30000000
1!
#35000000
0!
#40000000
0$
1!
#45000000
0!
#50000000
b1 .
1(
1!
#55000000
0!
#60000000
0(
b10 .
1!
#65000000
0!
#70000000
b11 .
1(
1!
#75000000
0!
#80000000
0(
b100 .
1!
#85000000
0!
#90000000
b0 "
1#
b101 .
1(
1!
#95000000
0!
#100000000
0#
0(
b0 4
b110 .
1!
#105000000
0!
#110000000
b1100100 "
1#
b111 .
1(
1!
#115000000
0!
#120000000
0#
0(
b1100100 4
b1000 .
1!
#125000000
0!
#130000000
b11001000 "
1#
b1001 .
1(
1!
#135000000
0!
#140000000
0#
0(
b11001000 4
b1010 .
1!
#145000000
0!
#150000000
b100101100 "
1#
b1011 .
1(
1!
#155000000
0!
#160000000
0#
0(
b100101100 4
b1100 .
1!
#165000000
0!
#170000000
b110010000 "
1#
b1101 .
1(
1!
#175000000
0!
#180000000
0#
0(
b110010000 4
b1110 .
1!
#185000000
0!
#190000000
b111110100 "
1#
b1111 .
1(
1!
#195000000
0!
#200000000
0#
0(
b111110100 4
b10000 .
1!
#205000000
0!
#210000000
b1001011000 "
1#
b10001 .
1(
1!
#215000000
0!
#220000000
0#
0(
b1001011000 4
b10010 .
1!
#225000000
0!
#230000000
b1010111100 "
1#
b10011 .
1(
1!
#235000000
0!
#240000000
0#
0(
b1010111100 4
b10100 .
1!
#245000000
0!
#250000000
b1100100000 "
1#
b10101 .
1(
1!
#255000000
0!
#260000000
0#
0(
b1100100000 4
b10110 .
1!
#265000000
0!
#270000000
b1110000100 "
1#
b10111 .
1(
1!
#275000000
0!
#280000000
0#
0(
b1110000100 4
b11000 .
1!
#285000000
0!
#290000000
b1111101000 "
1#
b11001 .
1(
1!
#295000000
0!
#300000000
0#
0(
b1111101000 4
b11010 .
1!
#305000000
0!
#310000000
b10001001100 "
1#
b11011 .
1(
1!
#315000000
0!
#320000000
0#
0(
b10001001100 4
b11100 .
1!
#325000000
0!
#330000000
b10010110000 "
1#
b11101 .
1(
1!
#335000000
0!
#340000000
0#
0(
b10010110000 4
b11110 .
1!
#345000000
0!
#350000000
b10100010100 "
1#
b11111 .
1(
1!
#355000000
0!
#360000000
0#
0(
b10100010100 4
b100000 .
1!
#365000000
0!
#370000000
b10101111000 "
1#
b100001 .
1(
1!
#375000000
0!
#380000000
0#
0(
b10101111000 4
b100010 .
1!
#385000000
0!
#390000000
b10111011100 "
1#
b100011 .
1(
1!
#395000000
0!
#400000000
0#
0(
b10111011100 4
b100100 .
1!
#405000000
0!
#410000000
b11001000000 "
1#
b100101 .
1(
1!
#415000000
0!
#420000000
0#
0(
b11001000000 4
b100110 .
1!
#425000000
0!
#430000000
b11010100100 "
1#
b100111 .
1(
1!
#435000000
0!
#440000000
0#
0(
b11010100100 4
b101000 .
1!
#445000000
0!
#450000000
b11100001000 "
1#
b101001 .
1(
1!
#455000000
0!
#460000000
0#
0(
b11100001000 4
b101010 .
1!
#465000000
0!
#470000000
b11101101100 "
1#
b101011 .
1(
1!
#475000000
0!
#480000000
0#
0(
b11101101100 4
b101100 .
1!
#485000000
0!
#490000000
b101101 .
1(
1!
#490000001
1$
#490041666
0!
#490083331
0(
b10010110000 4
b0 .
1!
#490124996
0!
#490166661
1!
#490208326
0!
#490249991
1!
#490291656
0!
#490333321
1!
#490374986
0!
#490416651
0$
1!
#490458316
0!
#490499981
b1 .
1(
1!
#490541646
0!
#490583311
0(
b10 .
1!
#490624976
0!
#490666641
b11 .
1(
1!
#490708306
0!
#490749971
0(
b100 .
1!
#490791636
0!
#490833301
b10010101111 "
1#
b101 .
1(
1!
#490874966
0!
#490916631
0#
0(
b10010101111 4
b110 .
1!
#490958296
0!
#490999961
1%
b111 .
1(
1!
#491041626
0!
#491083291
15
0(
b1000 .
1!
#491124956
0!
#491166621
b1001 .
1(
16
1!
#491208286
0!
#491249951
0'
17
0(
b1010 .
1!
#491291616
0!
#491333281
b1011 .
1(
1!
#491374946
0!
#491416611
0(
b1100 .
1!
#491458276
0!
#491499941
b1101 .
1(
1!
#491541606
0!
#491583271
0(
b1110 .
1!
#491624936
0!
#491666601
b1111 .
1(
1!
#491708266
0!
#491749931
0(
b10000 .
1!
#491791596
0!
#491833261
b10001 .
1(
1!
#491874926
0!
#491916591
0(
b10010 .
1!
#491958256
0!
#491999921
b10011 .
1(
1!
#492041586
0!
#492083251
0(
b10100 .
1!
#492124916
0!
#492166581
b10101 .
1(
1!
#492208246
0!
#492249911
0(
b10110 .
1!
#492291576
0!
#492333241
b10111 .
1(
1!
#492374906
0!
#492416571
0(
b11000 .
1!
#492458236
0!
#492499901
b11001 .
1(
1!
#492541566
0!
#492583231
0(
b11010 .
1!
#492624896
0!
#492666561
b11011 .
1(
1!
#492708226
0!
#492749891
0(
b11100 .
1!
#492791556
0!
#492833221
b11101 .
1(
1!
#492874886
0!
#492916551
0(
b11110 .
1!
#492958216
0!
#492999881
b11111 .
1(
1!
#493041546
0!
#493083211
0(
b100000 .
1!
#493124876
0!
#493166541
b100001 .
1(
1!
#493208206
0!
#493249871
0(
b100010 .
1!
#493291536
0!
#493333201
b100011 .
1(
1!
#493374866
0!
#493416531
0(
b100100 .
1!
#493458196
0!
#493499861
b100101 .
1(
1!
#493541526
0!
#493583191
0(
b100110 .
1!
#493624856
0!
#493666521
b100111 .
1(
1!
#493708186
0!
#493749851
0(
b101000 .
1!
#493791516
0!
#493833181
b101001 .
1(
1!
#493874846
0!
#493916511
0(
b101010 .
1!
#493958176
0!
#493999841
b101011 .
1(
1!
#494041506
0!
#494083171
0(
b101100 .
1!
#494124836
0!
#494166501
b101101 .
1(
1!
#494208166
0!
#494249831
0(
b101110 .
1!
#494291496
0!
#494333161
b101111 .
1(
1!
#494374826
0!
#494416491
0(
b110000 .
1!
#494458156
0!
#494499821
b110001 .
1(
1!
#494541486
0!
#494583151
0(
b110010 .
1!
#494624816
0!
#494666481
b110011 .
1(
1!
#494708146
0!
#494749811
0(
b110100 .
1!
#494791476
0!
#494833141
b110101 .
1(
1!
#494874806
0!
#494916471
0(
b110110 .
1!
#494958136
0!
#494999801
b110111 .
1(
1!
#495041466
0!
#495083131
0(
b111000 .
1!
#495124796
0!
#495166461
b111001 .
1(
1!
#495208126
0!
#495249791
0(
b111010 .
1!
#495291456
0!
#495333121
b111011 .
1(
1!
#495374786
0!
#495416451
0(
b111100 .
1!
#495458116
0!
#495499781
b111101 .
1(
1!
#495541446
0!
#495583111
0(
b111110 .
1!
#495624776
0!
#495666441
b111111 .
1(
1!
#495708106
0!
#495749771
0(
b1000000 .
1!
#495791436
0!
#495833101
b1000001 .
1(
1!
#495874766
0!
#495916431
0(
b1000010 .
1!
#495958096
0!
#495999761
b1000011 .
1(
1!
#495999961
0%
#496041426
0!
#496083091
05
0(
b1000100 .
1!
#496124756
0!
#496166421
b1000101 .
1(
06
1!
#496208086
0!
#496249751
07
0(
b1000110 .
1!
#496291416
0!
#496333081
b1000111 .
1(
1!
#496374746
0!
#496416411
0(
b1001000 .
1!
#496458076
0!
#496499741
b1001001 .
1(
1!
#496541406
0!
#496583071
0(
b1001010 .
1!
#496624736
0!
#496666401
b1001011 .
1(
1!
#496708066
0!
#496749731
0(
b1001100 .
1!
#496791396
0!
#496833061
b1001101 .
1(
1!
#496874726
0!
#496916391
0(
b1001110 .
1!
#496958056
0!
#496999721
b1001111 .
1(
1!
#497041386
0!
#497083051
0(
b1010000 .
1!
#497124716
0!
#497166381
b1010001 .
1(
1!
#497208046
0!
#497249711
0(
b1010010 .
1!
#497291376
0!
#497333041
b1010011 .
1(
1!
#497374706
0!
#497416371
0(
b1010100 .
1!
#497458036
0!
#497499701
b1010101 .
1(
1!
#497541366
0!
#497583031
0(
b1010110 .
1!
#497624696
0!
#497666361
b1010111 .
1(
1!
#497708026
0!
#497749691
0(
b1011000 .
1!
#497791356
0!
#497833021
b1011001 .
1(
1!
#497874686
0!
#497916351
0(
b1011010 .
1!
#497958016
0!
#497999681
b1011011 .
1(
1!
#498041346
0!
#498083011
0(
b1011100 .
1!
#498124676
0!
#498166341
b1011101 .
1(
1!
#498208006
0!
#498249671
0(
b1011110 .
1!
#498291336
0!
#498333001
b1011111 .
1(
1!
#498374666
0!
#498416331
0(
b1100000 .
1!
#498457996
0!
#498499661
b1100001 .
1(
1!
#498541326
0!
#498582991
0(
b1100010 .
1!
#498624656
0!
#498666321
b1100011 .
1(
1!
#498707986
0!
#498749651
0(
b1100100 .
1!
#498791316
0!
#498832981
b1100101 .
1(
1!
#498874646
0!
#498916311
0(
b1100110 .
1!
#498957976
0!
#498999641
b1100111 .
1(
1!
#499041306
0!
#499082971
0(
b1101000 .
1!
#499124636
0!
#499166301
b1101001 .
1(
1!
#499207966
0!
#499249631
0(
b1101010 .
1!
#499291296
0!
#499332961
b1101011 .
1(
1!
#499374626
0!
#499416291
0(
b1101100 .
1!
#499457956
0!
#499499621
b1101101 .
1(
1!
#499541286
0!
#499582951
0(
b1101110 .
1!
#499624616
0!
#499666281
b1101111 .
1(
1!
#499707946
0!
#499749611
0(
b1110000 .
1!
#499791276
0!
#499832941
b1110001 .
1(
1!
#499874606
0!
#499916271
0(
b1110010 .
1!
#499957936
0!
#499999601
b1110011 .
1(
1!
#500041266
0!
#500082931
0(
b1110100 .
1!
#500124596
0!
#500166261
b1110101 .
1(
1!
#500207926
0!
#500249591
0(
b1110110 .
1!
#500291256
0!
#500332921
b1110111 .
1(
1!
#500374586
0!
#500416251
0(
b1111000 .
1!
#500457916
0!
#500499581
b1111001 .
1(
1!
#500541246
0!
#500582911
0(
b1111010 .
1!
#500624576
0!
#500666241
b1111011 .
1(
1!
#500707906
0!
#500749571
0(
b1111100 .
1!
#500791236
0!
#500832901
b1111101 .
1(
1!
#500874566
0!
#500916231
0(
b1111110 .
1!
#500957896
0!
#500999561
b1111111 .
1(
1!
#500999961
1%
#501041226
0!
#501082891
15
0(
b10000000 .
1!
#501124556
0!
#501166221
1'
b10000001 .
1(
16
1!
#501207886
0!
#501249551
0'
17
0(
b10000010 .
b1 /
1!
#501291216
0!
#501332881
b10000011 .
1(
1!
#501374546
0!
#501416211
0(
b10000100 .
1!
#501457876
0!
#501499541
b10000101 .
1(
1!
#501541206
0!
#501582871
0(
b10000110 .
1!
#501624536
0!
#501666201
b10000111 .
1(
1!
#501707866
0!
#501749531
0(
b10001000 .
1!
#501791196
0!
#501832861
b10001001 .
1(
1!
#501874526
0!
#501916191
0(
b10001010 .
1!
#501957856
0!
#501999521
b10001011 .
1(
1!
#502041186
0!
#502082851
0(
b10001100 .
1!
#502124516
0!
#502166181
b10001101 .
1(
1!
#502207846
0!
#502249511
0(
b10001110 .
1!
#502291176
0!
#502332841
b10001111 .
1(
1!
#502374506
0!
#502416171
0(
b10010000 .
1!
#502457836
0!
#502499501
b10010001 .
1(
1!
#502541166
0!
#502582831
0(
b10010010 .
1!
#502624496
0!
#502666161
b10010011 .
1(
1!
#502707826
0!
#502749491
0(
b10010100 .
1!
#502791156
0!
#502832821
b10010101 .
1(
1!
#502874486
0!
#502916151
0(
b10010110 .
1!
#502957816
0!
#502999481
b10010111 .
1(
1!
#503041146
0!
#503082811
0(
b10011000 .
1!
#503124476
0!
#503166141
b10011001 .
1(
1!
#503207806
0!
#503249471
0(
b10011010 .
1!
#503291136
0!
#503332801
b10011011 .
1(
1!
#503374466
0!
#503416131
0(
b10011100 .
1!
#503457796
0!
#503499461
b10011101 .
1(
1!
#503541126
0!
#503582791
0(
b10011110 .
1!
#503624456
0!
#503666121
b10011111 .
1(
1!
#503707786
0!
#503749451
0(
b10100000 .
1!
#503791116
0!
#503832781
b10100001 .
1(
1!
#503874446
0!
#503916111
0(
b10100010 .
1!
#503957776
0!
#503999441
b10100011 .
1(
1!
#504041106
0!
#504082771
0(
b10100100 .
1!
#504124436
0!
#504166101
b10100101 .
1(
1!
#504207766
0!
#504249431
0(
b10100110 .
1!
#504291096
0!
#504332761
b10100111 .
1(
1!
#504374426
0!
#504416091
0(
b10101000 .
1!
#504457756
0!
#504499421
b10101001 .
1(
1!
#504541086
0!
#504582751
0(
b10101010 .
1!
#504624416
0!
#504666081
b10101011 .
1(
1!
#504707746
0!
#504749411
0(
b10101100 .
1!
#504791076
0!
#504832741
b10101101 .
1(
1!
#504874406
0!
#504916071
0(
b10101110 .
1!
#504957736
0!
#504999401
b10101111 .
1(
1!
#505041066
0!
#505082731
0(
b10110000 .
1!
#505124396
0!
#505166061
b10110001 .
1(
1!
#505207726
0!
#505249391
0(
b10110010 .
1!
#505291056
0!
#505332721
b10110011 .
1(
1!
#505374386
0!
#505416051
0(
b10110100 .
1!
#505457716
0!
#505499381
b10110101 .
1(
1!
#505541046
0!
#505582711
0(
b10110110 .
1!
#505624376
0!
#505666041
b10110111 .
1(
1!
#505707706
0!
#505749371
0(
b10111000 .
1!
#505791036
0!
#505832701
b10111001 .
1(
1!
#505874366
0!
#505916031
0(
b10111010 .
1!
#505957696
0!
#505999361
b10111011 .
1(
1!
#505999961
0%
#506041026
0!
#506082691
05
0(
b10111100 .
1!
#506124356
0!
#506166021
b10111101 .
1(
06
1!
#506207686
0!
#506249351
07
0(
b10111110 .
1!
#506291016
0!
#506332681
b10111111 .
1(
1!
#506374346
0!
#506416011
0(
b11000000 .
1!
#506457676
0!
#506499341
b11000001 .
1(
1!
#506541006
0!
#506582671
0(
b11000010 .
1!
#506624336
0!
#506666001
b11000011 .
1(
1!
#506707666
0!
#506749331
0(
b11000100 .
1!
#506790996
0!
#506832661
b11000101 .
1(
1!
#506874326
0!
#506915991
0(
b11000110 .
1!
#506957656
0!
#506999321
b11000111 .
1(
1!
#507040986
0!
#507082651
0(
b11001000 .
1!
#507124316
0!
#507165981
b11001001 .
1(
1!
#507207646
0!
#507249311
0(
b11001010 .
1!
#507290976
0!
#507332641
b11001011 .
1(
1!
#507374306
0!
#507415971
0(
b11001100 .
1!
#507457636
0!
#507499301
b11001101 .
1(
1!
#507540966
0!
#507582631
0(
b11001110 .
1!
#507624296
0!
#507665961
b11001111 .
1(
1!
#507707626
0!
#507749291
0(
b11010000 .
1!
#507790956
0!
#507832621
b11010001 .
1(
1!
#507874286
0!
#507915951
0(
b11010010 .
1!
#507957616
0!
#507999281
b11010011 .
1(
1!
#508040946
0!
#508082611
0(
b11010100 .
1!
#508124276
0!
#508165941
b11010101 .
1(
1!
#508207606
0!
#508249271
0(
b11010110 .
1!
#508290936
0!
#508332601
b11010111 .
1(
1!
#508374266
0!
#508415931
0(
b11011000 .
1!
#508457596
0!
#508499261
b11011001 .
1(
1!
#508540926
0!
#508582591
0(
b11011010 .
1!
#508624256
0!
#508665921
b11011011 .
1(
1!
#508707586
0!
#508749251
0(
b11011100 .
1!
#508790916
0!
#508832581
b11011101 .
1(
1!
#508874246
0!
#508915911
0(
b11011110 .
1!
#508957576
0!
#508999241
b11011111 .
1(
1!
#509040906
0!
#509082571
0(
b11100000 .
1!
#509124236
0!
#509165901
b11100001 .
1(
1!
#509207566
0!
#509249231
0(
b11100010 .
1!
#509290896
0!
#509332561
b11100011 .
1(
1!
#509374226
0!
#509415891
0(
b11100100 .
1!
#509457556
0!
#509499221
b11100101 .
1(
1!
#509540886
0!
#509582551
0(
b11100110 .
1!
#509624216
0!
#509665881
b11100111 .
1(
1!
#509707546
0!
#509749211
0(
b11101000 .
1!
#509790876
0!
#509832541
b11101001 .
1(
1!
#509874206
0!
#509915871
0(
b11101010 .
1!
#509957536
0!
#509999201
b11101011 .
1(
1!
#510040866
0!
#510082531
0(
b11101100 .
1!
#510124196
0!
#510165861
b11101101 .
1(
1!
#510207526
0!
#510249191
0(
b11101110 .
1!
#510290856
0!
#510332521
b11101111 .
1(
1!
#510374186
0!
#510415851
0(
b11110000 .
1!
#510457516
0!
#510499181
b11110001 .
1(
1!
#510540846
0!
#510582511
0(
b11110010 .
1!
#510624176
0!
#510665841
b11110011 .
1(
1!
#510707506
0!
#510749171
0(
b11110100 .
1!
#510790836
0!
#510832501
b11110101 .
1(
1!
#510874166
0!
#510915831
0(
b11110110 .
1!
#510957496
0!
#510999161
b11110111 .
1(
1!
#510999961
1%
#511040826
0!
#511082491
15
0(
b11111000 .
1!
#511124156
0!
#511165821
1'
b11111001 .
1(
16
1!
#511207486
0!
#511249151
0'
17
0(
b11111010 .
b10 /
1!
#511290816
0!
#511332481
b11111011 .
1(
1!
#511374146
0!
#511415811
0(
b11111100 .
1!
#511457476
0!
#511499141
b11111101 .
1(
1!
#511540806
0!
#511582471
0(
b11111110 .
1!
#511624136
0!
#511665801
b11111111 .
1(
1!
#511707466
0!
#511749131
0(
b100000000 .
1!
#511790796
0!
#511832461
b100000001 .
1(
1!
#511874126
0!
#511915791
0(
b100000010 .
1!
#511957456
0!
#511999121
b100000011 .
1(
1!
#512040786
0!
#512082451
0(
b100000100 .
1!
#512124116
0!
#512165781
b100000101 .
1(
1!
#512207446
0!
#512249111
0(
b100000110 .
1!
#512290776
0!
#512332441
b100000111 .
1(
1!
#512374106
0!
#512415771
0(
b100001000 .
1!
#512457436
0!
#512499101
b100001001 .
1(
1!
#512540766
0!
#512582431
0(
b100001010 .
1!
#512624096
0!
#512665761
b100001011 .
1(
1!
#512707426
0!
#512749091
0(
b100001100 .
1!
#512790756
0!
#512832421
b100001101 .
1(
1!
#512874086
0!
#512915751
0(
b100001110 .
1!
#512957416
0!
#512999081
b100001111 .
1(
1!
#513040746
0!
#513082411
0(
b100010000 .
1!
#513124076
0!
#513165741
b100010001 .
1(
1!
#513207406
0!
#513249071
0(
b100010010 .
1!
#513290736
0!
#513332401
b100010011 .
1(
1!
#513374066
0!
#513415731
0(
b100010100 .
1!
#513457396
0!
#513499061
b100010101 .
1(
1!
#513540726
0!
#513582391
0(
b100010110 .
1!
#513624056
0!
#513665721
b100010111 .
1(
1!
#513707386
0!
#513749051
0(
b100011000 .
1!
#513790716
0!
#513832381
b100011001 .
1(
1!
#513874046
0!
#513915711
0(
b100011010 .
1!
#513957376
0!
#513999041
b100011011 .
1(
1!
#514040706
0!
#514082371
0(
b100011100 .
1!
#514124036
0!
#514165701
b100011101 .
1(
1!
#514207366
0!
#514249031
0(
b100011110 .
1!
#514290696
0!
#514332361
b100011111 .
1(
1!
#514374026
0!
#514415691
0(
b100100000 .
1!
#514457356
0!
#514499021
b100100001 .
1(
1!
#514540686
0!
#514582351
0(
b100100010 .
1!
#514624016
0!
#514665681
b100100011 .
1(
1!
#514707346
0!
#514749011
0(
b100100100 .
1!
#514790676
0!
#514832341
b100100101 .
1(
1!
#514874006
0!
#514915671
0(
b100100110 .
1!
#514957336
0!
#514999001
b100100111 .
1(
1!
#515040666
0!
#515082331
0(
b100101000 .
1!
#515123996
0!
#515165661
b100101001 .
1(
1!
#515207326
0!
#515248991
0(
b100101010 .
1!
#515290656
0!
#515332321
b100101011 .
1(
1!
#515373986
0!
#515415651
0(
b100101100 .
1!
#515457316
0!
#515498981
b100101101 .
1(
1!
#515540646
0!
#515582311
0(
b100101110 .
1!
#515623976
0!
#515665641
b100101111 .
1(
1!
#515707306
0!
#515748971
0(
b100110000 .
1!
#515790636
0!
#515832301
b100110001 .
1(
1!
#515873966
0!
#515915631
0(
b100110010 .
1!
#515957296
0!
#515998961
b100110011 .
1(
1!
#515999961
0%
#516040626
0!
#516082291
05
0(
b100110100 .
1!
#516123956
0!
#516165621
b100110101 .
1(
06
1!
#516207286
0!
#516248951
07
0(
b100110110 .
1!
#516290616
0!
#516332281
b100110111 .
1(
1!
#516373946
0!
#516415611
0(
b100111000 .
1!
#516457276
0!
#516498941
b100111001 .
1(
1!
#516540606
0!
#516582271
0(
b100111010 .
1!
#516623936
0!
#516665601
b100111011 .
1(
1!
#516707266
0!
#516748931
0(
b100111100 .
1!
#516790596
0!
#516832261
b100111101 .
1(
1!
#516873926
0!
#516915591
0(
b100111110 .
1!
#516957256
0!
#516998921
b100111111 .
1(
1!
#517040586
0!
#517082251
0(
b101000000 .
1!
#517123916
0!
#517165581
b101000001 .
1(
1!
#517207246
0!
#517248911
0(
b101000010 .
1!
#517290576
0!
#517332241
b101000011 .
1(
1!
#517373906
0!
#517415571
0(
b101000100 .
1!
#517457236
0!
#517498901
b101000101 .
1(
1!
#517540566
0!
#517582231
0(
b101000110 .
1!
#517623896
0!
#517665561
b101000111 .
1(
1!
#517707226
0!
#517748891
0(
b101001000 .
1!
#517790556
0!
#517832221
b101001001 .
1(
1!
#517873886
0!
#517915551
0(
b101001010 .
1!
#517957216
0!
#517998881
b101001011 .
1(
1!
#518040546
0!
#518082211
0(
b101001100 .
1!
#518123876
0!
#518165541
b101001101 .
1(
1!
#518207206
0!
#518248871
0(
b101001110 .
1!
#518290536
0!
#518332201
b101001111 .
1(
1!
#518373866
0!
#518415531
0(
b101010000 .
1!
#518457196
0!
#518498861
b101010001 .
1(
1!
#518540526
0!
#518582191
0(
b101010010 .
1!
#518623856
0!
#518665521
b101010011 .
1(
1!
#518707186
0!
#518748851
0(
b101010100 .
1!
#518790516
0!
#518832181
b101010101 .
1(
1!
#518873846
0!
#518915511
0(
b101010110 .
1!
#518957176
0!
#518998841
b101010111 .
1(
1!
#519040506
0!
#519082171
0(
b101011000 .
1!
#519123836
0!
#519165501
b101011001 .
1(
1!
#519207166
0!
#519248831
0(
b101011010 .
1!
#519290496
0!
#519332161
b101011011 .
1(
1!
#519373826
0!
#519415491
0(
b101011100 .
1!
#519457156
0!
#519498821
b101011101 .
1(
1!
#519540486
0!
#519582151
0(
b101011110 .
1!
#519623816
0!
#519665481
b101011111 .
1(
1!
#519707146
0!
#519748811
0(
b101100000 .
1!
#519790476
0!
#519832141
b101100001 .
1(
1!
#519873806
0!
#519915471
0(
b101100010 .
1!
#519957136
0!
#519998801
b101100011 .
1(
1!
#520040466
0!
#520082131
0(
b101100100 .
1!
#520123796
0!
#520165461
b101100101 .
1(
1!
#520207126
0!
#520248791
0(
b101100110 .
1!
#520290456
0!
#520332121
b101100111 .
1(
1!
#520373786
0!
#520415451
0(
b101101000 .
1!
#520457116
0!
#520498781
b101101001 .
1(
1!
#520540446
0!
#520582111
0(
b101101010 .
1!
#520623776
0!
#520665441
b101101011 .
1(
1!
#520707106
0!
#520748771
0(
b101101100 .
1!
#520790436
0!
#520832101
b101101101 .
1(
1!
#520873766
0!
#520915431
0(
b101101110 .
1!
#520957096
0!
#520998761
b101101111 .
1(
1!
#520999961
1%
#521040426
0!
#521082091
15
0(
b101110000 .
1!
#521123756
0!
#521165421
1'
b101110001 .
1(
16
1!
#521207086
0!
#521248751
0'
17
0(
b101110010 .
b11 /
1!
#521290416
0!
#521332081
b101110011 .
1(
1!
#521373746
0!
#521415411
0(
b101110100 .
1!
#521457076
0!
#521498741
b101110101 .
1(
1!
#521540406
0!
#521582071
0(
b101110110 .
1!
#521623736
0!
#521665401
b101110111 .
1(
1!
#521707066
0!
#521748731
0(
b101111000 .
1!
#521790396
0!
#521832061
b101111001 .
1(
1!
#521873726
0!
#521915391
0(
b101111010 .
1!
#521957056
0!
#521998721
b101111011 .
1(
1!
#522040386
0!
#522082051
0(
b101111100 .
1!
#522123716
0!
#522165381
b101111101 .
1(
1!
#522207046
0!
#522248711
0(
b101111110 .
1!
#522290376
0!
#522332041
b101111111 .
1(
1!
#522373706
0!
#522415371
0(
b110000000 .
1!
#522457036
0!
#522498701
b110000001 .
1(
1!
#522540366
0!
#522582031
0(
b110000010 .
1!
#522623696
0!
#522665361
b110000011 .
1(
1!
#522707026
0!
#522748691
0(
b110000100 .
1!
#522790356
0!
#522832021
b110000101 .
1(
1!
#522873686
0!
#522915351
0(
b110000110 .
1!
#522957016
0!
#522998681
b110000111 .
1(
1!
#523040346
0!
#523082011
0(
b110001000 .
1!
#523123676
0!
#523165341
b110001001 .
1(
1!
#523207006
0!
#523248671
0(
b110001010 .
1!
#523290336
0!
#523332001
b110001011 .
1(
1!
#523373666
0!
#523415331
0(
b110001100 .
1!
#523456996
0!
#523498661
b110001101 .
1(
1!
#523540326
0!
#523581991
0(
b110001110 .
1!
#523623656
0!
#523665321
b110001111 .
1(
1!
#523706986
0!
#523748651
0(
b110010000 .
1!
#523790316
0!
#523831981
b110010001 .
1(
1!
#523873646
0!
#523915311
0(
b110010010 .
1!
#523956976
0!
#523998641
b110010011 .
1(
1!
#524040306
0!
#524081971
0(
b110010100 .
1!
